{
 "e6_rungs_used": {
  "2": 7,
  "3": 9,
  "5": 3,
  "6": 27,
  "7": 3,
  "8": 3
 },
 "su3_realized_centrals": {
  "2": [
   {
    "q": 3,
    "p": 3,
    "a": 1,
    "j": 10,
    "ordT": 15,
    "ordA1modn": 20
   },
   {
    "q": 5,
    "p": 5,
    "a": 1,
    "j": null,
    "ordT": 15,
    "ordA1modn": 20
   }
  ],
  "3": [
   {
    "q": 2,
    "p": 2,
    "a": 1,
    "j": 12,
    "ordT": 18,
    "ordA1modn": 12
   },
   {
    "q": 9,
    "p": 3,
    "a": 2,
    "j": 6,
    "ordT": 18,
    "ordA1modn": 12
   }
  ],
  "4": [
   {
    "q": 3,
    "p": 3,
    "a": 1,
    "j": null,
    "ordT": 21,
    "ordA1modn": 8
   },
   {
    "q": 7,
    "p": 7,
    "a": 1,
    "j": 4,
    "ordT": 21,
    "ordA1modn": 8
   }
  ],
  "5": [
   {
    "q": 3,
    "p": 3,
    "a": 1,
    "j": 6,
    "ordT": 24,
    "ordA1modn": 12
   },
   {
    "q": 8,
    "p": 2,
    "a": 3,
    "j": null,
    "ordT": 24,
    "ordA1modn": 12
   }
  ],
  "6": [
   {
    "q": 27,
    "p": 3,
    "a": 3,
    "j": 18,
    "ordT": 27,
    "ordA1modn": 36
   }
  ],
  "7": [
   {
    "q": 2,
    "p": 2,
    "a": 1,
    "j": 60,
    "ordT": 30,
    "ordA1modn": 60
   },
   {
    "q": 3,
    "p": 3,
    "a": 1,
    "j": 30,
    "ordT": 30,
    "ordA1modn": 60
   },
   {
    "q": 5,
    "p": 5,
    "a": 1,
    "j": null,
    "ordT": 30,
    "ordA1modn": 60
   }
  ],
  "8": [
   {
    "q": 3,
    "p": 3,
    "a": 1,
    "j": 10,
    "ordT": 33,
    "ordA1modn": 20
   },
   {
    "q": 11,
    "p": 11,
    "a": 1,
    "j": null,
    "ordT": 33,
    "ordA1modn": 20
   }
  ],
  "9": [
   {
    "q": 4,
    "p": 2,
    "a": 2,
    "j": null,
    "ordT": 36,
    "ordA1modn": 12
   },
   {
    "q": 9,
    "p": 3,
    "a": 2,
    "j": 6,
    "ordT": 36,
    "ordA1modn": 12
   }
  ],
  "10": [
   {
    "q": 3,
    "p": 3,
    "a": 1,
    "j": 14,
    "ordT": 39,
    "ordA1modn": 28
   },
   {
    "q": 13,
    "p": 13,
    "a": 1,
    "j": null,
    "ordT": 39,
    "ordA1modn": 28
   }
  ],
  "11": [
   {
    "q": 2,
    "p": 2,
    "a": 1,
    "j": 24,
    "ordT": 42,
    "ordA1modn": 24
   },
   {
    "q": 3,
    "p": 3,
    "a": 1,
    "j": null,
    "ordT": 42,
    "ordA1modn": 24
   },
   {
    "q": 7,
    "p": 7,
    "a": 1,
    "j": 12,
    "ordT": 42,
    "ordA1modn": 24
   }
  ],
  "12": [
   {
    "q": 5,
    "p": 5,
    "a": 1,
    "j": null,
    "ordT": 45,
    "ordA1modn": 60
   },
   {
    "q": 9,
    "p": 3,
    "a": 2,
    "j": 30,
    "ordT": 45,
    "ordA1modn": 60
   }
  ]
 },
 "sign_table": [
  {
   "stage": "E6",
   "k": 2,
   "p": 7,
   "a": 1,
   "q": 7,
   "j": 12,
   "N_total": 9,
   "ordT": 84,
   "kind": "scalar",
   "scalar": 1,
   "dev": 1.2382503484952849e-49,
   "n_plus": 3,
   "n_minus": 0,
   "n_other": 0,
   "dim_odd": 3,
   "c": "78/7",
   "c_mod24": "78/7"
  },
  {
   "stage": "E6",
   "k": 3,
   "p": 3,
   "a": 2,
   "q": 9,
   "j": 30,
   "N_total": 20,
   "ordT": 180,
   "kind": "scalar",
   "scalar": -1,
   "dev": 6.929192603548418e-50,
   "n_plus": 0,
   "n_minus": 8,
   "n_other": 0,
   "dim_odd": 8,
   "c": "78/5",
   "c_mod24": "78/5"
  },
  {
   "stage": "E6",
   "k": 5,
   "p": 3,
   "a": 1,
   "q": 3,
   "j": 18,
   "N_total": 78,
   "ordT": 204,
   "kind": "mixed",
   "scalar": null,
   "dev": 2.0,
   "n_plus": 18,
   "n_minus": 16,
   "n_other": 0,
   "dim_odd": 34,
   "involution_dev": 3.263763324255218e-49,
   "c": "390/17",
   "c_mod24": "390/17"
  },
  {
   "stage": "E6",
   "k": 6,
   "p": 3,
   "a": 3,
   "q": 27,
   "j": 18,
   "N_total": 139,
   "ordT": 108,
   "kind": "scalar",
   "scalar": 1,
   "dev": 1.2857965840876117e-49,
   "n_plus": 61,
   "n_minus": 0,
   "n_other": 0,
   "dim_odd": 61,
   "c": "26",
   "c_mod24": "2"
  },
  {
   "stage": "E6",
   "k": 7,
   "p": 3,
   "a": 1,
   "q": 3,
   "j": 18,
   "N_total": 231,
   "ordT": 228,
   "kind": "mixed",
   "scalar": null,
   "dev": 2.0,
   "n_plus": 49,
   "n_minus": 56,
   "n_other": 0,
   "dim_odd": 105,
   "involution_dev": 2.3361551797938106e-49,
   "c": "546/19",
   "c_mod24": "90/19"
  },
  {
   "stage": "E6",
   "k": 8,
   "p": 3,
   "a": 1,
   "q": 3,
   "j": 30,
   "N_total": 372,
   "ordT": 60,
   "kind": "mixed",
   "scalar": null,
   "dev": 2.0,
   "n_plus": 78,
   "n_minus": 92,
   "n_other": 0,
   "dim_odd": 170,
   "involution_dev": 9.66889341463063e-49,
   "c": "156/5",
   "c_mod24": "36/5"
  },
  {
   "stage": "SU3",
   "k": 2,
   "p": 3,
   "a": 1,
   "q": 3,
   "j": 10,
   "N_total": 6,
   "ordT": 15,
   "kind": "scalar",
   "scalar": 1,
   "dev": 4.35864894852469e-50,
   "n_plus": 2,
   "n_minus": 0,
   "n_other": 0,
   "dim_odd": 2,
   "c": "16/5",
   "c_mod24": "16/5"
  },
  {
   "stage": "SU3",
   "k": 3,
   "p": 2,
   "a": 1,
   "q": 2,
   "j": 12,
   "N_total": 10,
   "ordT": 18,
   "kind": "scalar",
   "scalar": 1,
   "dev": 1.0678671033823396e-49,
   "n_plus": 4,
   "n_minus": 0,
   "n_other": 0,
   "dim_odd": 4,
   "c": "4",
   "c_mod24": "4"
  },
  {
   "stage": "SU3",
   "k": 3,
   "p": 3,
   "a": 2,
   "q": 9,
   "j": 6,
   "N_total": 10,
   "ordT": 18,
   "kind": "scalar",
   "scalar": -1,
   "dev": 5.323619499919853e-50,
   "n_plus": 0,
   "n_minus": 4,
   "n_other": 0,
   "dim_odd": 4,
   "c": "4",
   "c_mod24": "4"
  },
  {
   "stage": "SU3",
   "k": 4,
   "p": 7,
   "a": 1,
   "q": 7,
   "j": 4,
   "N_total": 15,
   "ordT": 21,
   "kind": "mixed",
   "scalar": null,
   "dev": 2.0,
   "n_plus": 2,
   "n_minus": 4,
   "n_other": 0,
   "dim_odd": 6,
   "involution_dev": 3.8019587602160373e-50,
   "c": "32/7",
   "c_mod24": "32/7"
  },
  {
   "stage": "SU3",
   "k": 5,
   "p": 3,
   "a": 1,
   "q": 3,
   "j": 6,
   "N_total": 21,
   "ordT": 24,
   "kind": "mixed",
   "scalar": null,
   "dev": 2.0,
   "n_plus": 5,
   "n_minus": 4,
   "n_other": 0,
   "dim_odd": 9,
   "involution_dev": 1.2099712546569035e-49,
   "c": "5",
   "c_mod24": "5"
  },
  {
   "stage": "SU3",
   "k": 6,
   "p": 3,
   "a": 3,
   "q": 27,
   "j": 18,
   "N_total": 28,
   "ordT": 27,
   "kind": "scalar",
   "scalar": -1,
   "dev": 1.1948901462301517e-49,
   "n_plus": 0,
   "n_minus": 12,
   "n_other": 0,
   "dim_odd": 12,
   "c": "16/3",
   "c_mod24": "16/3"
  },
  {
   "stage": "SU3",
   "k": 7,
   "p": 2,
   "a": 1,
   "q": 2,
   "j": 60,
   "N_total": 36,
   "ordT": 30,
   "kind": "scalar",
   "scalar": 1,
   "dev": 8.958498132425252e-49,
   "n_plus": 16,
   "n_minus": 0,
   "n_other": 0,
   "dim_odd": 16,
   "c": "28/5",
   "c_mod24": "28/5"
  },
  {
   "stage": "SU3",
   "k": 7,
   "p": 3,
   "a": 1,
   "q": 3,
   "j": 30,
   "N_total": 36,
   "ordT": 30,
   "kind": "mixed",
   "scalar": null,
   "dev": 2.0,
   "n_plus": 8,
   "n_minus": 8,
   "n_other": 0,
   "dim_odd": 16,
   "involution_dev": 8.969589489043652e-49,
   "c": "28/5",
   "c_mod24": "28/5"
  },
  {
   "stage": "SU3",
   "k": 8,
   "p": 3,
   "a": 1,
   "q": 3,
   "j": 10,
   "N_total": 45,
   "ordT": 33,
   "kind": "mixed",
   "scalar": null,
   "dev": 2.0,
   "n_plus": 10,
   "n_minus": 10,
   "n_other": 0,
   "dim_odd": 20,
   "involution_dev": 1.7676973315606556e-49,
   "c": "64/11",
   "c_mod24": "64/11"
  },
  {
   "stage": "SU3",
   "k": 9,
   "p": 3,
   "a": 2,
   "q": 9,
   "j": 6,
   "N_total": 55,
   "ordT": 36,
   "kind": "mixed",
   "scalar": null,
   "dev": 2.0,
   "n_plus": 13,
   "n_minus": 12,
   "n_other": 0,
   "dim_odd": 25,
   "involution_dev": 1.6204629778885713e-49,
   "c": "6",
   "c_mod24": "6"
  },
  {
   "stage": "SU3",
   "k": 10,
   "p": 3,
   "a": 1,
   "q": 3,
   "j": 14,
   "N_total": 66,
   "ordT": 39,
   "kind": "mixed",
   "scalar": null,
   "dev": 2.0,
   "n_plus": 14,
   "n_minus": 16,
   "n_other": 0,
   "dim_odd": 30,
   "involution_dev": 3.267780764816454e-49,
   "c": "80/13",
   "c_mod24": "80/13"
  },
  {
   "stage": "SU3",
   "k": 11,
   "p": 2,
   "a": 1,
   "q": 2,
   "j": 24,
   "N_total": 78,
   "ordT": 42,
   "kind": "scalar",
   "scalar": 1,
   "dev": 6.526566150069055e-49,
   "n_plus": 36,
   "n_minus": 0,
   "n_other": 0,
   "dim_odd": 36,
   "c": "44/7",
   "c_mod24": "44/7"
  },
  {
   "stage": "SU3",
   "k": 11,
   "p": 7,
   "a": 1,
   "q": 7,
   "j": 12,
   "N_total": 78,
   "ordT": 42,
   "kind": "mixed",
   "scalar": null,
   "dev": 2.0,
   "n_plus": 20,
   "n_minus": 16,
   "n_other": 0,
   "dim_odd": 36,
   "involution_dev": 6.526566150069055e-49,
   "c": "44/7",
   "c_mod24": "44/7"
  },
  {
   "stage": "SU3",
   "k": 12,
   "p": 3,
   "a": 2,
   "q": 9,
   "j": 30,
   "N_total": 91,
   "ordT": 45,
   "kind": "mixed",
   "scalar": null,
   "dev": 1.0,
   "n_plus": 26,
   "n_minus": 16,
   "n_other": 0,
   "dim_odd": 42,
   "involution_dev": 1.8214945836738898e-48,
   "c": "32/5",
   "c_mod24": "32/5"
  }
 ],
 "n_scalar_rows": 9,
 "n_mixed_rows": 11,
 "gates": {
  "f2_e6_table_reproduced": true,
  "e6_k6_scalar": 1,
  "e6_k6_dev": 1.2857965840876117e-49,
  "su3_k6_scalar": -1,
  "su3_k6_dev": 1.1948901462301517e-49
 },
 "verdict": "chi_block(-I_q) is NOT a universally-defined scalar: it is an exact scalar at only a subset of realized centrals (see n_scalar_rows / n_mixed_rows); at the rest the central element acts as a genuine, exactly-certified +-1 involution SPLITTING the theta-odd block (no single sign exists there). Sealed candidate (i) [(-1)^(a*f(c mod 24))] is analytically impossible in general (see the same-k multi-a witness in the log) and empirically non-fitting. Sealed candidates (ii) [local Legendre/Kronecker symbols at p] and (iii) [dim_odd parity] do not fit all scalar rows either, except the restricted 'stage-flip * (p|3)' sub-case (fits all p!=3 scalar rows, silent on p=3). The single best near-miss found (not one of the 3 sealed families as literally stated) is scalar=(-1)^(a-1) [+1 odd a, -1 even a], fitting all scalar rows except SU(3) k=6 -- precisely the one point where the pre-existing E-type/A-type deep-3 dichotomy (E6 kills deep-3, SU(3) 'kills nothing') is already known to diverge."
}